isee/__init__.py
isee/common.py
isee/file_modification_utils.py
isee/generation_utils.py
isee/git_utils.py
isee/local_cli.py
isee/pip_utils.py
isee/pylint_log_synopsis.py
isee-0.2.75.dist-info/licenses/LICENSE
tests/__init__.py
tests/conftest.py
tests/test_local_cli.py
tests/test_local_cli_integration.py
isee-0.2.75.dist-info/METADATA
isee-0.2.75.dist-info/WHEEL
isee-0.2.75.dist-info/entry_points.txt
isee-0.2.75.dist-info/top_level.txt
isee-0.2.75.dist-info/RECORD
