Metadata-Version: 2.4
Name: isee
Version: 0.2.75
Summary: Python continuous integration (CI) support tools.
Home-page: https://github.com/i2mint/isee
License: MIT
Project-URL: Homepage, https://github.com/i2mint/isee
Platform: any
Requires-Python: >=3.10
License-File: LICENSE
Requires-Dist: semver==2.13.0
Requires-Dist: wads
Provides-Extra: testing
Dynamic: license-file
